nocomentariosN2T/__init__.py
nocomentariosN2T/cli.py
nocomentariosN2T/nocomentariosN2T.py
nocomentariosN2T-0.2.0.dist-info/DESCRIPTION.rst
nocomentariosN2T-0.2.0.dist-info/METADATA
nocomentariosN2T-0.2.0.dist-info/RECORD
nocomentariosN2T-0.2.0.dist-info/WHEEL
nocomentariosN2T-0.2.0.dist-info/entry_points.txt
nocomentariosN2T-0.2.0.dist-info/metadata.json
nocomentariosN2T-0.2.0.dist-info/top_level.txt
