Metadata-Version: 2.0
Name: nocomentariosN2T
Version: 0.2.0
Summary: Elimina comentarios de archivos de Nand2Tetris
Home-page: https://github.com/caladdd/nocomentariosN2T
Author: Juan Pablo Calad
Author-email: juanpablo.calad@gmail.com
License: MIT license
Keywords: nocomentariosN2T
Platform: UNKNOWN
Classifier: Development Status :: 2 - Pre-Alpha
Classifier: Intended Audience :: Developers
Classifier: License :: OSI Approved :: MIT License
Classifier: Natural Language :: English
Classifier: Programming Language :: Python :: 2
Classifier: Programming Language :: Python :: 2.7
Classifier: Programming Language :: Python :: 3
Classifier: Programming Language :: Python :: 3.4
Classifier: Programming Language :: Python :: 3.5
Classifier: Programming Language :: Python :: 3.6
Requires-Dist: Click (>=6.0)
